{
  "id": "2897666",
  "name": "红旗",
  "font_family": "iconfont",
  "css_prefix_text": "icon-",
  "description": "",
  "glyphs": [
    {
      "icon_id": "1304894",
      "name": "展开菜单",
      "font_class": "zhankaicaidan",
      "unicode": "e624",
      "unicode_decimal": 58916
    },
    {
      "icon_id": "5831258",
      "name": "错",
      "font_class": "cuo",
      "unicode": "e63f",
      "unicode_decimal": 58943
    },
    {
      "icon_id": "12515511",
      "name": "下箭头",
      "font_class": "arrow-down",
      "unicode": "e610",
      "unicode_decimal": 58896
    }
  ]
}
